qdiv/__init__.py
qdiv/citations.py
qdiv/data_object.py
qdiv/diversity/__init__.py
qdiv/diversity/alpha_div.py
qdiv/diversity/beta_div.py
qdiv/example_data/Modin2025_CoverM.tsv
qdiv/example_data/Modin2025_SingleM.ebd
qdiv/example_data/Modin2025_gtdbtk.ar53.summary.tsv
qdiv/example_data/Modin2025_gtdbtk.bac120.summary.tsv
qdiv/example_data/Modin2025_metadata.csv
qdiv/example_data/Modin2025_tree.nwk
qdiv/example_data/Saheb-Alam2019_meta.csv
qdiv/example_data/Saheb-Alam2019_seq_dada2.fasta
qdiv/example_data/Saheb-Alam2019_seq_deblur.fasta
qdiv/example_data/Saheb-Alam2019_tab_dada2.tsv
qdiv/example_data/Saheb-Alam2019_tab_deblur.tsv
qdiv/example_data/Saheb-Alam2019_tax_dada2.tsv
qdiv/example_data/Saheb-Alam2019_tax_deblur.tsv
qdiv/example_data/Saheb-Alam2019_tree_dada2.nwk
qdiv/example_data/Saheb-Alam2019_tree_deblur.nwk
qdiv/example_data/loader.py
qdiv/io/__init__.py
qdiv/io/files.py
qdiv/io/subset.py
qdiv/model/__init__.py
qdiv/model/null.py
qdiv/model/simulate.py
qdiv/plot/__init__.py
qdiv/plot/diversity_plots.py
qdiv/plot/ordination_plots.py
qdiv/plot/relative_abundance_plots.py
qdiv/sequences/__init__.py
qdiv/sequences/accelerate.py
qdiv/sequences/sequence_comparisons.py
qdiv/stats/__init__.py
qdiv/stats/distance_tests.py
qdiv/stats/ordination_calculations.py
qdiv/utils/__init__.py
qdiv/utils/data_utils.py
qdiv/utils/phylo_utils.py
qdiv/utils/plot_utils.py
qdiv-4.0.0.dist-info/licenses/LICENSE
qdiv-4.0.0.dist-info/METADATA
qdiv-4.0.0.dist-info/WHEEL
qdiv-4.0.0.dist-info/top_level.txt
qdiv-4.0.0.dist-info/RECORD
