Metadata-Version: 2.4
Name: qdiv
Version: 4.0.0
Summary: Microbial diversity analysis toolkit
Author-email: Oskar Modin <omvatten@gmail.com>
License: BSD 3-Clause License
Requires-Python: >=3.8
License-File: LICENSE
Requires-Dist: pandas>=1.3
Requires-Dist: numpy>=1.21
Requires-Dist: matplotlib>=3.5
Requires-Dist: tqdm>=4.60
Provides-Extra: accelerate
Requires-Dist: numba>=0.57; extra == "accelerate"
Provides-Extra: docs
Requires-Dist: sphinx>=8; extra == "docs"
Requires-Dist: sphinx-rtd-theme>=3; extra == "docs"
Requires-Dist: myst-parser>=4; extra == "docs"
Requires-Dist: nbsphinx>=0.9.5; extra == "docs"
Dynamic: license-file
